plexsearch/__init__.py
plexsearch/api.py
plexsearch/config.py
plexsearch/context.py
plexsearch/core.py
plexsearch/update_checker.py
plexsearch-0.2.2.dist-info/LICENSE
plexsearch-0.2.2.dist-info/METADATA
plexsearch-0.2.2.dist-info/WHEEL
plexsearch-0.2.2.dist-info/entry_points.txt
plexsearch-0.2.2.dist-info/RECORD
