Metadata-Version: 2.1
Name: plexsearch
Version: 0.2.2
Summary: A powerful Python tool for performing technical searches using the Perplexity API
Home-page: https://github.com/tom-doerr/perplexity_search
License: MIT
Keywords: search,perplexity,ai,llm
Author: Tom Doerr
Requires-Python: >=3.7
Classifier: Development Status :: 3 - Alpha
Classifier: Intended Audience :: Developers
Classifier: License :: OSI Approved :: MIT License
Classifier: Operating System :: OS Independent
Classifier: Programming Language :: Python :: 3
Classifier: Programming Language :: Python :: 3.7
Classifier: Programming Language :: Python :: 3.8
Classifier: Programming Language :: Python :: 3.9
Classifier: Programming Language :: Python :: 3.10
Classifier: Programming Language :: Python :: 3.11
Classifier: Programming Language :: Python :: 3.12
Classifier: Programming Language :: Python :: 3.13
Requires-Dist: feedparser (>=6.0.0,<7.0.0)
Requires-Dist: packaging (>=23.0,<24.0)
Requires-Dist: requests (>=2.25.0,<3.0.0)
Requires-Dist: rich (>=13.7.0,<14.0.0)
Project-URL: Bug Tracker, https://github.com/tom-doerr/perplexity_search/issues
Project-URL: Documentation, https://github.com/tom-doerr/perplexity_search#readme
Project-URL: Repository, https://github.com/tom-doerr/perplexity_search
